HISTORY.md
LICENSE
MANIFEST.in
README.md
requirements.txt
requirements_dev.txt
setup.cfg
setup.py
versioneer.py
simple_event_bus/__init__.py
simple_event_bus/_version.py
simple_event_bus/errors.py
simple_event_bus.egg-info/PKG-INFO
simple_event_bus.egg-info/SOURCES.txt
simple_event_bus.egg-info/dependency_links.txt
simple_event_bus.egg-info/entry_points.txt
simple_event_bus.egg-info/requires.txt
simple_event_bus.egg-info/top_level.txt
simple_event_bus/core/__init__.py
simple_event_bus/core/async_event_bus.py
simple_event_bus/core/event.py
simple_event_bus/core/event_bus.py
simple_event_bus/event_source/__init__.py
tests/__init__.py
tests/test_core.py
tests/test_simple_event_bus.py