Metadata-Version: 2.1
Name: simple-event-bus
Version: 0.0.4
Summary: a simple python event bus
Home-page: https://github.com/AngusWG/simple-event-bus
Author: AngusWG
Author-email: z740713651@outlook.com
License: MIT license
Keywords: simple_event_bus
Platform: UNKNOWN
Classifier: Development Status :: 2 - Pre-Alpha
Classifier: Intended Audience :: Developers
Classifier: License :: OSI Approved :: MIT License
Classifier: Natural Language :: English
Classifier: Programming Language :: Python :: 3.7
Classifier: Programming Language :: Python :: 3.8
Classifier: Programming Language :: Python :: 3.9
Requires-Python: >=3.6
Provides-Extra: dev_require
License-File: LICENSE
